tcpb/__init__.py
tcpb/clients.py
tcpb/config.py
tcpb/exceptions.py
tcpb/serial_utils.py
tcpb/terachem_server.proto
tcpb/terachem_server_pb2.py
tcpb/terachem_server_pb2.pyi
tcpb/utils.py
tcpb-0.14.3.dist-info/LICENSE
tcpb-0.14.3.dist-info/METADATA
tcpb-0.14.3.dist-info/WHEEL
tcpb-0.14.3.dist-info/RECORD
