Metadata-Version: 2.3
Name: tcpb
Version: 0.14.3
Summary: A Python client for TeraChem's protocol buffer API.
License: MIT
Author: Colton Hicks
Author-email: github@coltonhicks.com
Requires-Python: >=3.9,<4.0
Classifier: Intended Audience :: Science/Research
Classifier: License :: OSI Approved :: MIT License
Classifier: Operating System :: OS Independent
Classifier: Programming Language :: Python
Classifier: Programming Language :: Python :: 3
Classifier: Programming Language :: Python :: 3.9
Classifier: Programming Language :: Python :: 3.10
Classifier: Programming Language :: Python :: 3.11
Classifier: Programming Language :: Python :: 3.12
Classifier: Programming Language :: Python :: 3.13
Classifier: Programming Language :: Python :: 3 :: Only
Classifier: Topic :: Software Development
Classifier: Topic :: Software Development :: Libraries
Classifier: Topic :: Software Development :: Libraries :: Python Modules
Classifier: Typing :: Typed
Requires-Dist: google (==1.9.3)
Requires-Dist: httpx (>=0.27)
Requires-Dist: numpy (>=1.13)
Requires-Dist: protobuf (==3.20.1)
Requires-Dist: pydantic (>=2.0.0,!=2.4.0)
Requires-Dist: pydantic-settings (>=2.0.3,<3.0.0)
Requires-Dist: qcio (>=0.11.9)
Project-URL: Documentation, https://mtzgroup.github.io/tcpb-client/
Project-URL: Homepage, https://github.com/mtzgroup/tcpb-client
Project-URL: Repository, https://github.com/mtzgroup/tcpb-client
